tree_sitter_elixir/_binding.abi3.so
tree_sitter_elixir/py.typed
tree_sitter_elixir/binding.c
tree_sitter_elixir/__init__.py
tree_sitter_elixir/__init__.pyi
tree_sitter_elixir/queries/highlights.scm
tree_sitter_elixir/queries/tags.scm
tree_sitter_elixir/queries/injections.scm
tree_sitter_elixir-0.3.4.dist-info/NOTICE
tree_sitter_elixir-0.3.4.dist-info/LICENSE
tree_sitter_elixir-0.3.4.dist-info/WHEEL
tree_sitter_elixir-0.3.4.dist-info/RECORD
tree_sitter_elixir-0.3.4.dist-info/top_level.txt
tree_sitter_elixir-0.3.4.dist-info/METADATA
