Metadata-Version: 2.2
Name: tree-sitter-elixir
Version: 0.3.4
Summary: Elixir grammar for tree-sitter
License: Apache-2.0
Project-URL: Homepage, https://github.com/elixir-lang/tree-sitter-elixir
Keywords: incremental,parsing,tree-sitter,elixir
Classifier: Intended Audience :: Developers
Classifier: License :: OSI Approved :: MIT License
Classifier: Topic :: Software Development :: Compilers
Classifier: Topic :: Text Processing :: Linguistic
Classifier: Typing :: Typed
Requires-Python: >=3.9
License-File: LICENSE
License-File: NOTICE
Provides-Extra: core
Requires-Dist: tree-sitter~=0.23; extra == "core"
